acelib/__init__.py
acelib/block_assignment.py
acelib/block_design.py
acelib/constants.py
acelib/deconvolution.py
acelib/deconvolved_peptide.py
acelib/deconvolved_peptide_set.py
acelib/defaults.py
acelib/logger.py
acelib/main.py
acelib/peptide.py
acelib/peptide_set.py
acelib/plate_readout.py
acelib/plate_readout_entry.py
acelib/plate_well.py
acelib/pool.py
acelib/sequence_features.py
acelib/types.py
acelib/utilities.py
acelib/cli/__init__.py
acelib/cli/cli_deconvolve.py
acelib/cli/cli_generate.py
acelib/cli/cli_main.py
acelib/cli/cli_verify.py
acelib/resources/models/trained_model_w_data_augmentation_b3000.pt
ace_elispot-0.1.3.0.dist-info/METADATA
ace_elispot-0.1.3.0.dist-info/WHEEL
ace_elispot-0.1.3.0.dist-info/entry_points.txt
ace_elispot-0.1.3.0.dist-info/top_level.txt
ace_elispot-0.1.3.0.dist-info/RECORD
