Metadata-Version: 2.1
Name: ace-elispot
Version: 0.1.3.0
Summary: ELISpot configuration generation and pool spot count deconvolution
Project-URL: Homepage, https://github.com/pirl-unc/ace
Project-URL: Bug Tracker, https://github.com/pirl-unc/ace
Keywords: elispot,assay optimization,immunological assay,deconvolution,high-throughput assay
Classifier: Programming Language :: Python :: Implementation :: CPython
Classifier: Programming Language :: Python :: Implementation :: PyPy
Requires-Python: ==3.10.13
